{
  "gitSyncId": "6704ace79f84094942828663_c3e3f382-1d6c-4fd1-b032-db6416fa6182",
  "id": "Page1_SelectQuery",
  "pluginId": "postgres-plugin",
  "pluginType": "DB",
  "unpublishedAction": {
    "actionConfiguration": {
      "body": "SELECT * FROM kal_meta_data.\"kal_smartcare_common_asset_attributes\"\nWHERE \"asset_id\" ilike '%{{data_table.searchText || \"\"}}%'\nORDER BY \"{{data_table.sortOrder.column || 'asset_id'}}\" {{data_table.sortOrder.order || 'ASC'}}\nLIMIT {{data_table.pageSize}}\nOFFSET {{(data_table.pageNo - 1) * data_table.pageSize}};",
      "encodeParamsToggle": true,
      "paginationType": "NONE",
      "pluginSpecifiedTemplates": [
        {
          "value": false
        }
      ],
      "timeoutInMillisecond": 10000
    },
    "confirmBeforeExecute": false,
    "datasource": {
      "id": "postgres metadata",
      "isAutoGenerated": false,
      "name": "postgres metadata",
      "pluginId": "postgres-plugin"
    },
    "executeOnLoad": true,
    "name": "SelectQuery",
    "pageId": "Page1",
    "userSetOnLoad": true
  }
}